setup.py
miscreant/__init__.py
miscreant/aead.py
miscreant/block.py
miscreant/ct.py
miscreant/ctz.py
miscreant/exceptions.py
miscreant/stream.py
miscreant.egg-info/PKG-INFO
miscreant.egg-info/SOURCES.txt
miscreant.egg-info/dependency_links.txt
miscreant.egg-info/not-zip-safe
miscreant.egg-info/requires.txt
miscreant.egg-info/top_level.txt
miscreant/aes/__init__.py
miscreant/aes/siv.py
miscreant/mac/__init__.py
miscreant/mac/pmac.py
tests/support/__init__.py
tests/support/test_vectors.py