Metadata-Version: 1.1
Name: miscreant
Version: 0.3.0
Summary: Misuse-resistant authenticated symmetric encryption
Home-page: https://github.com/miscreant/miscreant/tree/master/python/
Author: Tony Arcieri
Author-email: bascule@gmail.com
License: MIT license
Keywords: cryptography,encryption,security,streaming
Platform: UNKNOWN
Classifier: Development Status :: 2 - Pre-Alpha
Classifier: Intended Audience :: Developers
Classifier: License :: OSI Approved :: MIT License
Classifier: Natural Language :: English
